netto/__init__.py
netto/config.py
netto/const.py
netto/main.py
netto/social_security.py
netto/taxes_income.py
netto/taxes_other.py
netto-0.1.0.dist-info/LICENSE
netto-0.1.0.dist-info/METADATA
netto-0.1.0.dist-info/WHEEL
netto-0.1.0.dist-info/top_level.txt
netto-0.1.0.dist-info/RECORD
