Metadata-Version: 2.1
Name: netto
Version: 0.1.0
Summary: German income tax (Einkommensteuer) and social security (Sozialabgaben) calculator
Author-email: Martin Klein <hi@martinklein.co>
Project-URL: Homepage, https://github.com/0-k/netto
Project-URL: Documentation, https://netto.readthedocs.io/en/latest/
Project-URL: Bug Tracker, https://github.com/0-k/netto/issues
Classifier: Programming Language :: Python :: 3
Classifier: License :: OSI Approved :: MIT License
Classifier: Operating System :: OS Independent
Requires-Python: >=3.7
License-File: LICENSE
